Metadata-Version: 2.1
Name: httpie-adobeio
Version: 0.0.1
Summary: AdobeIO plugin for HTTPie.
Home-page: https://github.com/cpilsworth/httpie-cpilsworth
Author: Chris Pilsworth
Author-email: cpilsworth@gmail.com
License: Apache License 2.0
Download-URL: https://github.com/cpilsworth/httpie-adobeio/releases/download/0.0.1/httpie-adobeio-0.0.1.tar.gz
Platform: UNKNOWN
Classifier: Development Status :: 5 - Production/Stable
Classifier: Programming Language :: Python
Classifier: Environment :: Plugins
Classifier: License :: OSI Approved :: Apache Software License
Classifier: Topic :: Internet :: WWW/HTTP
Classifier: Topic :: Utilities
Requires-Python: >=3.6
